{
  "groups": [
    {
      "name": "spring.datasource.druid",
      "type": "com.web2020.mall.support.DruidDataSourceProperties",
      "sourceType": "com.web2020.mall.support.DruidDataSourceProperties"
    }
  ],
  "properties": [
    {
      "name": "spring.datasource.druid.driver-class-name",
      "type": "java.lang.String",
      "sourceType": "com.web2020.mall.support.DruidDataSourceProperties"
    },
    {
      "name": "spring.datasource.druid.initial-size",
      "type": "java.lang.Integer",
      "sourceType": "com.web2020.mall.support.DruidDataSourceProperties"
    },
    {
      "name": "spring.datasource.druid.jdbc-url",
      "type": "java.lang.String",
      "sourceType": "com.web2020.mall.support.DruidDataSourceProperties"
    },
    {
      "name": "spring.datasource.druid.max-active",
      "type": "java.lang.Integer",
      "sourceType": "com.web2020.mall.support.DruidDataSourceProperties"
    },
    {
      "name": "spring.datasource.druid.max-wait",
      "type": "java.lang.Long",
      "sourceType": "com.web2020.mall.support.DruidDataSourceProperties",
      "defaultValue": 0
    },
    {
      "name": "spring.datasource.druid.min-idle",
      "type": "java.lang.Integer",
      "sourceType": "com.web2020.mall.support.DruidDataSourceProperties"
    },
    {
      "name": "spring.datasource.druid.password",
      "type": "java.lang.String",
      "sourceType": "com.web2020.mall.support.DruidDataSourceProperties"
    },
    {
      "name": "spring.datasource.druid.pool-prepared-statements",
      "type": "java.lang.Boolean",
      "sourceType": "com.web2020.mall.support.DruidDataSourceProperties",
      "defaultValue": false
    },
    {
      "name": "spring.datasource.druid.username",
      "type": "java.lang.String",
      "sourceType": "com.web2020.mall.support.DruidDataSourceProperties"
    }
  ],
  "hints": []
}